MANIFEST.in
setup.py
Pale.egg-info/PKG-INFO
Pale.egg-info/SOURCES.txt
Pale.egg-info/dependency_links.txt
Pale.egg-info/entry_points.txt
Pale.egg-info/pbr.json
Pale.egg-info/top_level.txt
bin/paledoc
pale/__init__.py
pale/config.py
pale/context.py
pale/doc.py
pale/endpoint.py
pale/meta.py
pale/resource.py
pale/response.py
pale/utils.py
pale/adapters/__init__.py
pale/adapters/flask.py
pale/adapters/webapp2.py
pale/arguments/__init__.py
pale/arguments/base.py
pale/arguments/boolean.py
pale/arguments/number.py
pale/arguments/scope.py
pale/arguments/string.py
pale/arguments/url.py
pale/errors/__init__.py
pale/errors/api_error.py
pale/errors/base.py
pale/errors/validation.py
pale/fields/__init__.py
pale/fields/base.py
pale/fields/boolean.py
pale/fields/integer.py
pale/fields/links.py
pale/fields/resource.py
pale/fields/scope.py
pale/fields/string.py
pale/fields/timestamp.py
pale/fields/url.py
tests/__init__.py
tests/test_fields.py
tests/test_flask_adapter.py
tests/test_paledoc.py
tests/test_webapp2_adapter.py
tests/example_app/__init__.py
tests/example_app/flask_app.py
tests/example_app/models.py
tests/example_app/webapp2_app.py
tests/example_app/api/__init__.py
tests/example_app/api/endpoints.py
tests/example_app/api/resources.py