Metadata-Version: 1.0
Name: Pale
Version: 0.5.1
Summary: Pale is a framework for crafting HTTP APIs.
Home-page: https://github.com/Loudr/pale
Author: R. Kevin Nelson
Author-email: kevin@rkn.la
License: MIT License
Platform: UNKNOWN
